dash_cm/__init__.py
dash_cm/__main__.py
dash_cm/serve_local.py
dash_cm/start_case.py
dash_cm/build/_redirects
dash_cm/build/asset-manifest.json
dash_cm/build/index.html
dash_cm/build/manifest.json
dash_cm/build/favicon/favicon.ico
dash_cm/build/static/logo.svg
dash_cm/build/static/css/main.feeb957e.css
dash_cm/build/static/css/main.feeb957e.css.map
dash_cm/build/static/icons/logo_32.png
dash_cm/build/static/icons/logo_512.png
dash_cm/build/static/illustrations/illustration_404.svg
dash_cm/build/static/js/787.9b918496.chunk.js
dash_cm/build/static/js/787.9b918496.chunk.js.map
dash_cm/build/static/js/main.cfb55d71.js
dash_cm/build/static/js/main.cfb55d71.js.LICENSE.txt
dash_cm/build/static/js/main.cfb55d71.js.map
dash_cm-0.1.25.dist-info/LICENSE
dash_cm-0.1.25.dist-info/METADATA
dash_cm-0.1.25.dist-info/WHEEL
dash_cm-0.1.25.dist-info/top_level.txt
dash_cm-0.1.25.dist-info/RECORD
